.DS_Store
pyxlsx/Cell.py
pyxlsx/ExcelReader.py
pyxlsx/ReadOnlyCell.py
pyxlsx/Series.py
pyxlsx/Workbook.py
pyxlsx/WorkbookParser.py
pyxlsx/Worksheet.py
pyxlsx/WorksheetParser.py
pyxlsx/WorksheetReader.py
pyxlsx/__init__.py
pyxlsx/_constants.py
pyxlsx/new_xlsx.py
pyxlsx/open_xlsx.py
pyxlsx/utils.py
pyxlsx-1.1.2.dist-info/METADATA
pyxlsx-1.1.2.dist-info/WHEEL
pyxlsx-1.1.2.dist-info/top_level.txt
pyxlsx-1.1.2.dist-info/RECORD
