Metadata-Version: 2.1
Name: pyxlsx
Version: 1.1.2
Summary: UNKNOWN
Home-page: https://github.com/fortfall/pyxlsx
Author: lihailin
License: MIT
Platform: UNKNOWN
Classifier: Programming Language :: Python :: 3
Classifier: License :: OSI Approved :: MIT License
Classifier: Operating System :: OS Independent
Requires-Python: >=3.5
Requires-Dist: openpyxl (>=3.0.3)
Requires-Dist: pycel
